MANIFEST.in
README.rst
setup.py
pygraphflow/__init__.py
pygraphflow/datatype.py
pygraphflow/g.py
pygraphflow/q.py
pygraphflow.egg-info/PKG-INFO
pygraphflow.egg-info/SOURCES.txt
pygraphflow.egg-info/dependency_links.txt
pygraphflow.egg-info/not-zip-safe
pygraphflow.egg-info/requires.txt
pygraphflow.egg-info/top_level.txt