Metadata-Version: 1.0
Name: pygraphflow
Version: 0.1.1.2
Summary: A driver for GraphFlow DB
Home-page: http://www.graphflow.io/
Author: GraphFlow Team
Author-email: amine.mhedhbi@uwaterloo.ca
License: MIT
Platform: UNKNOWN
